koii/__init__.py
koii-1.0.1.dist-info/METADATA
koii-1.0.1.dist-info/WHEEL
koii-1.0.1.dist-info/top_level.txt
koii-1.0.1.dist-info/RECORD
