Metadata-Version: 2.1
Name: koii
Version: 1.0.1
Summary: A python library to display routes in a flask application
Home-page: https://github.com/BolajiOlajide/koii-py
Author: Bolaji Olajide
License: MIT
Keywords: flask routes koii route
Platform: UNKNOWN
Classifier: Development Status :: 4 - Beta
Classifier: Intended Audience :: Developers
Classifier: License :: OSI Approved :: MIT License
Classifier: Programming Language :: Python :: 3
Classifier: Programming Language :: Python :: 3.5
Classifier: Programming Language :: Python :: 3.6
Classifier: Programming Language :: Python :: 3.7
Requires-Dist: colorama
Requires-Dist: tabulate
